Metadata-Version: 1.1
Name: visionfi
Version: 1.1.0
Summary: An library for visualization and outlier handling
Home-page: UNKNOWN
Author: Visiofi_Team
Author-email: UNKNOWN
License: MIT
Keywords: visualization
Platform: UNKNOWN
Classifier: Development Status :: 5 - Production/Stable
Classifier: Intended Audience :: Education
Classifier: Operating System :: Microsoft :: Windows :: Windows 10
Classifier: License :: OSI Approved :: MIT License
Classifier: Programming Language :: Python :: 3
